petrovisor/__init__.py
petrovisor/petrovisor.py
petrovisor/api/__init__.py
petrovisor/api/base.py
petrovisor/api/enums/__init__.py
petrovisor/api/enums/data_grids.py
petrovisor/api/enums/increments.py
petrovisor/api/enums/internal_dtypes.py
petrovisor/api/enums/items.py
petrovisor/api/enums/ml.py
petrovisor/api/methods/__init__.py
petrovisor/api/methods/contexts.py
petrovisor/api/methods/data_grids.py
petrovisor/api/methods/dataframes.py
petrovisor/api/methods/entities.py
petrovisor/api/methods/files.py
petrovisor/api/methods/items.py
petrovisor/api/methods/logs.py
petrovisor/api/methods/ml.py
petrovisor/api/methods/pivot_tables.py
petrovisor/api/methods/psharp.py
petrovisor/api/methods/reference_tables.py
petrovisor/api/methods/signals.py
petrovisor/api/methods/units.py
petrovisor/api/methods/workflows.py
petrovisor/api/methods/workspace_values.py
petrovisor/api/models/__init__.py
petrovisor/api/models/base_model.py
petrovisor/api/models/context.py
petrovisor/api/models/entity.py
petrovisor/api/models/entity_set.py
petrovisor/api/models/hierarchy.py
petrovisor/api/models/scope.py
petrovisor/api/models/signal.py
petrovisor/api/models/unit.py
petrovisor/api/protocols/__init__.py
petrovisor/api/protocols/protocols.py
petrovisor/api/utils/__init__.py
petrovisor/api/utils/datastructs.py
petrovisor/api/utils/general.py
petrovisor/api/utils/helper.py
petrovisor/api/utils/login.py
petrovisor/api/utils/requests.py
petrovisor/api/utils/validators.py
petrovisor/models/__init__.py
petrovisor/models/contexts_manager.py
petrovisor-0.1.9.dist-info/LICENSE
petrovisor-0.1.9.dist-info/METADATA
petrovisor-0.1.9.dist-info/WHEEL
petrovisor-0.1.9.dist-info/top_level.txt
petrovisor-0.1.9.dist-info/RECORD
