Metadata-Version: 2.1
Name: petrovisor
Version: 0.1.9
Summary: Python API for PetroVisor platform.
Home-page: https://github.com/Datagration/petrovisor-python-api
Author: Datagration Solutions Inc.
Author-email: "Datagration Solutions Inc." <developers@datagration.com>
License: MIT License
Project-URL: repository, https://github.com/Datagration/petrovisor-python-api
Classifier: Operating System :: OS Independent
Classifier: License :: OSI Approved :: MIT License
Classifier: Programming Language :: Python
Classifier: Programming Language :: Python :: 3
Classifier: Programming Language :: Python :: 3.7
Classifier: Programming Language :: Python :: 3.8
Classifier: Programming Language :: Python :: 3.9
Classifier: Programming Language :: Python :: 3.10
Classifier: Programming Language :: Python :: 3.11
Classifier: Programming Language :: Python :: 3.12
Requires-Python: >=3.7
License-File: LICENSE
Requires-Dist: requests
Requires-Dist: pandas
Requires-Dist: numpy
Requires-Dist: pydantic
Requires-Dist: openpyxl
Requires-Dist: xlsxwriter
Requires-Dist: typing-extensions
